pyopentsdb/__init__.py
pyopentsdb/aggregators.py
pyopentsdb/conf.py
pyopentsdb/config.py
pyopentsdb/dropcaches.py
pyopentsdb/errors.py
pyopentsdb/put.py
pyopentsdb/query.py
pyopentsdb/serializers.py
pyopentsdb/stats.py
pyopentsdb/suggest.py
pyopentsdb/tsdb.py
pyopentsdb/utils.py
pyopentsdb/version.py
pyopentsdb-0.2.1.dist-info/METADATA
pyopentsdb-0.2.1.dist-info/RECORD
pyopentsdb-0.2.1.dist-info/WHEEL
pyopentsdb-0.2.1.dist-info/entry_points.txt
pyopentsdb-0.2.1.dist-info/top_level.txt
