Metadata-Version: 2.1
Name: pyopentsdb
Version: 0.2.1
Summary: Python wrapper over OpenTSDB HTTP API
Home-page: https://github.com/s-t-e-a-l-t-h/pyopentsdb
Author: s-t-e-a-l-t-h
Author-email: UNKNOWN
License: UNKNOWN
Requires-Dist: requests
Provides-Extra: dev
